[{
		"method_name": "get_repos",
		"http_method": "GET",
		"url_endpoint": "/repos"
	},
	{
		"method_name": "get_repo_by_name",
		"http_method": "GET",
		"url_endpoint": "/repos/:repname"
	},
	{
		"method_name": "create_repo",
		"http_method": "POST",
		"url_endpoint": "/repos",
		"json_params": [
			"name",
			"server"
		]
	},
	{
		"method_name": "rename_repo",
		"http_method": "PUT",
		"url_endpoint": "/repos/:repname",
		"json_params": [
			"name"
		]
	},
	{
		"method_name": "delete_repo",
		"http_method": "DELETE",
		"url_endpoint": "/repos/:repname"
	},
	{
		"method_name": "get_workspaces",
		"http_method": "GET",
		"url_endpoint": "/wkspaces"
	},
	{
		"method_name": "get_workspace_by_name",
		"http_method": "GET",
		"url_endpoint": "/wkspaces/:wkname"
	},
	{
		"method_name": "create_workspace",
		"http_method": "POST",
		"url_endpoint": "/wkspaces",
		"json_params": [
			"name",
			"path",
			"repository"
		]
	},
	{
		"method_name": "rename_workspace",
		"http_method": "PATCH",
		"_comment": "Plastic documentation gives PUT for this method but it returns 405, PATCH is correct",
		"url_endpoint": "/wkspaces/:wkname",
		"json_params": [
			"name"
		]
	},
	{
		"method_name": "delete_workspace",
		"http_method": "DELETE",
		"url_endpoint": "/wkspaces/:wkname"
	},
	{
		"method_name": "get_branches",
		"http_method": "GET",
		"url_endpoint": "/repos/:repname/branches",
		"query": true
	},
	{
		"method_name": "get_branch",
		"http_method": "GET",
		"url_endpoint": "/repos/:repname/branches/:branchname"
	},
	{
		"method_name": "create_branch",
		"http_method": "POST",
		"url_endpoint": "/repos/:repname/branches",
		"json_params": [
			"name",
			"originType",
			"origin",
			"topLevel"
		]
	},
	{
		"method_name": "rename_branch",
		"http_method": "PATCH",
		"url_endpoint": "/repos/:repname/branches/:branchname",
		"json_params": [
			"name"
		]
	},
	{
		"method_name": "delete_branch",
		"http_method": "DELETE",
		"url_endpoint": "/repos/:repname/branches/:branchname"
	},
	{
		"method_name": "get_labels",
		"http_method": "GET",
		"url_endpoint": "/repos/:repname/labels",
		"query": true
	},
	{
		"method_name": "get_label",
		"http_method": "GET",
		"url_endpoint": "/repos/:repname/labels/:labelname"
	},
	{
		"method_name": "create_label",
		"http_method": "POST",
		"url_endpoint": "/repos/:repname/labels",
		"json_params": [
			"name",
			"changeset",
			"comment",
			"applyToXlinks"
		]
	},
	{
		"method_name": "rename_label",
		"http_method": "PATCH",
		"url_endpoint": "/repos/:repname/labels/:labelname",
		"json_params": [
			"name"
		]
	},
	{
		"method_name": "delete_label",
		"http_method": "DELETE",
		"url_endpoint": "/repos/:repname/labels/:labelname"
	},
	{
		"method_name": "get_changesets",
		"http_method": "GET",
		"url_endpoint": "/repos/:repname/changesets",
		"query": true
	},
	{
		"method_name": "get_changesets_by_branch",
		"http_method": "GET",
		"url_endpoint": "/repos/:repname/branches/:branchname/changesets",
		"query": true
	},
	{
		"method_name": "get_changeset",
		"http_method": "GET",
		"url_endpoint": "/repos/:repname/changesets/:changesetid"
	},
	{
		"method_name": "switch_workspace",
		"http_method": "POST",
		"url_endpoint": "/wkspaces/:wkname/switch",
		"json_params": [
			"objectType",
			"object"
		]
	}
]